odoo/addons/attribute_set/README.rst
odoo/addons/attribute_set/__init__.py
odoo/addons/attribute_set/__manifest__.py
odoo/addons/attribute_set/i18n/attribute_set.pot
odoo/addons/attribute_set/models/__init__.py
odoo/addons/attribute_set/models/attribute_attribute.py
odoo/addons/attribute_set/models/attribute_group.py
odoo/addons/attribute_set/models/attribute_option.py
odoo/addons/attribute_set/models/attribute_set.py
odoo/addons/attribute_set/models/attribute_set_owner.py
odoo/addons/attribute_set/readme/CONTRIBUTORS.rst
odoo/addons/attribute_set/readme/DESCRIPTION.rst
odoo/addons/attribute_set/readme/ROADMAP.rst
odoo/addons/attribute_set/readme/USAGE.rst
odoo/addons/attribute_set/security/attribute_security.xml
odoo/addons/attribute_set/security/ir.model.access.csv
odoo/addons/attribute_set/static/description/icon.png
odoo/addons/attribute_set/static/description/index.html
odoo/addons/attribute_set/tests/__init__.py
odoo/addons/attribute_set/tests/models.py
odoo/addons/attribute_set/tests/test_build_view.py
odoo/addons/attribute_set/tests/test_custom_attribute.py
odoo/addons/attribute_set/views/attribute_attribute_view.xml
odoo/addons/attribute_set/views/attribute_group_view.xml
odoo/addons/attribute_set/views/attribute_option_view.xml
odoo/addons/attribute_set/views/attribute_set_view.xml
odoo/addons/attribute_set/views/menu_view.xml
odoo/addons/attribute_set/wizard/__init__.py
odoo/addons/attribute_set/wizard/attribute_option_wizard.py
odoo/addons/attribute_set/wizard/attribute_option_wizard_view.xml
odoo12_addon_attribute_set-12.0.0.0.3.99.dev7.dist-info/METADATA
odoo12_addon_attribute_set-12.0.0.0.3.99.dev7.dist-info/WHEEL
odoo12_addon_attribute_set-12.0.0.0.3.99.dev7.dist-info/top_level.txt
odoo12_addon_attribute_set-12.0.0.0.3.99.dev7.dist-info/RECORD
